{"runId":"test-123","suiteName":"Test Suite","status":"RUNNING","startTime":"2026-03-05T19:15:01.318Z","endTime":null,"durationMs":1220,"testsPassed":0,"testsFailed":0,"testCases":[{"id":"tc1","name":"Test Case 1","status":"RUNNING","durationMs":0,"error":null,"steps":[{"id":0,"name":"goto_url https://example.com","status":"RUNNING","durationMs":0,"error":null}],"variables":{}}],"logs":[{"timestamp":"2026-03-05T19:15:02.039Z","level":"DEBUG","message":"Launched browser: chromium"},{"timestamp":"2026-03-05T19:15:02.534Z","level":"INFO","message":"[Test Case 1] Started."},{"timestamp":"2026-03-05T19:15:02.537Z","level":"DEBUG","message":"[Test Case 1] Executing: goto_url"}],"projectId":"default","triggeredBy":"API Worker"}